odoo/addons/sale_coupon_multiplier_free_product/README.rst
odoo/addons/sale_coupon_multiplier_free_product/__init__.py
odoo/addons/sale_coupon_multiplier_free_product/__manifest__.py
odoo/addons/sale_coupon_multiplier_free_product/i18n/es.po
odoo/addons/sale_coupon_multiplier_free_product/i18n/sale_coupon_multiplier_free_product.pot
odoo/addons/sale_coupon_multiplier_free_product/migrations/13.0.1.0.0/post_migration.py
odoo/addons/sale_coupon_multiplier_free_product/models/__init__.py
odoo/addons/sale_coupon_multiplier_free_product/models/sale_coupon.py
odoo/addons/sale_coupon_multiplier_free_product/models/sale_coupon_program.py
odoo/addons/sale_coupon_multiplier_free_product/models/sale_coupon_reward.py
odoo/addons/sale_coupon_multiplier_free_product/models/sale_order.py
odoo/addons/sale_coupon_multiplier_free_product/readme/CONFIGURE.rst
odoo/addons/sale_coupon_multiplier_free_product/readme/CONTRIBUTORS.rst
odoo/addons/sale_coupon_multiplier_free_product/readme/DESCRIPTION.rst
odoo/addons/sale_coupon_multiplier_free_product/readme/USAGE.rst
odoo/addons/sale_coupon_multiplier_free_product/static/description/icon.png
odoo/addons/sale_coupon_multiplier_free_product/static/description/index.html
odoo/addons/sale_coupon_multiplier_free_product/tests/__init__.py
odoo/addons/sale_coupon_multiplier_free_product/tests/test_website_sale_coupon_free_product.py
odoo/addons/sale_coupon_multiplier_free_product/views/sale_coupon_program_views.xml
odoo13_addon_sale_coupon_multiplier_free_product-13.0.1.0.3.dist-info/METADATA
odoo13_addon_sale_coupon_multiplier_free_product-13.0.1.0.3.dist-info/WHEEL
odoo13_addon_sale_coupon_multiplier_free_product-13.0.1.0.3.dist-info/top_level.txt
odoo13_addon_sale_coupon_multiplier_free_product-13.0.1.0.3.dist-info/RECORD
